sarthakai/__init__.py
sarthakai/common.py
sarthakai/models.py
sarthakai/chat/__init__.py
sarthakai/chat/text_preprocessing.py
sarthakai/documents/__init__.py
sarthakai/documents/doc_parsing/__init__.py
sarthakai/documents/doc_parsing/google.py
sarthakai/documents/doc_parsing/llamaparse.py
sarthakai/documents/doc_parsing/pypdf.py
sarthakai/documents/doc_parsing/reducto.py
sarthakai/entity_extraction/__init__.py
sarthakai/entity_extraction/instructor.py
sarthakai/entity_extraction/openai_function_calling.py
sarthakai/entity_extraction/tables.py
sarthakai/genai/__init__.py
sarthakai/genai/llm.py
sarthakai/genai/prompts.py
sarthakai/genai/tasks.py
sarthakai/splitting/__init__.py
sarthakai/splitting/by_sections.py
sarthakai/splitting/chunking.py
sarthakai/vector_search/__init__.py
sarthakai/vector_search/chromadb_utils.py
sarthakai/vector_search/cohere_utils.py
sarthakai/vector_search/common_utils.py
sarthakai/vector_search/pinecone_utils.py
sarthakai/web_data/__init__.py
sarthakai/web_data/apify.py
sarthakai/web_data/scraping.py
sarthakai-0.0.16.dist-info/.DS_Store
sarthakai-0.0.16.dist-info/LICENSE
sarthakai-0.0.16.dist-info/METADATA
sarthakai-0.0.16.dist-info/WHEEL
sarthakai-0.0.16.dist-info/top_level.txt
sarthakai-0.0.16.dist-info/RECORD
