Metadata-Version: 2.1
Name: sarthakai
Version: 0.0.16
Summary: UNKNOWN
Home-page: UNKNOWN
License: UNKNOWN
Platform: UNKNOWN
License-File: LICENSE
Requires-Dist: litellm (==1.66.1)
Requires-Dist: RapidFuzz (==3.10.1)
Requires-Dist: python-slugify (==8.0.4)
